[
  {
    "company_id": "H00700",
    "name_cn_full": "腾讯控股有限公司",
    "name_en_full": "Tencent Holdings Limited",
    "name_short": "腾讯",
    "stock_code": "00700.HK",
    "stock_exchange": "HKEX",
    "data_source": "HKEX 披露易",
    "collected_at": "2026-03-14T19:28:26.892804",
    "quality_level": "L1",
    "confidence_score": "1.0",
    "quality_score": 1.0,
    "cleaned_at": "2026-03-14T19:28:29.460527",
    "cleaned_version": "1.0"
  },
  {
    "company_id": "H09961",
    "name_cn_full": "阿里巴巴集团股份有限公司",
    "name_en_full": "Alibaba Group Holding Limited",
    "name_short": "阿里",
    "stock_code": "09961.HK",
    "stock_exchange": "HKEX",
    "data_source": "HKEX 披露易",
    "collected_at": "2026-03-14T19:28:26.892808",
    "quality_level": "L1",
    "confidence_score": "1.0",
    "quality_score": 1.0,
    "cleaned_at": "2026-03-14T19:28:29.460531",
    "cleaned_version": "1.0"
  },
  {
    "company_id": "H09618",
    "name_cn_full": "京东集团股份有限公司",
    "name_en_full": "Jd. Com, Inc. ",
    "name_short": "京东",
    "stock_code": "09618.HK",
    "stock_exchange": "HKEX",
    "data_source": "HKEX 披露易",
    "collected_at": "2026-03-14T19:28:26.892810",
    "quality_level": "L1",
    "confidence_score": "1.0",
    "quality_score": 1.0,
    "cleaned_at": "2026-03-14T19:28:29.460532",
    "cleaned_version": "1.0"
  },
  {
    "company_id": "H09888",
    "name_cn_full": "百度集团股份有限公司",
    "name_en_full": "Baidu, Inc. ",
    "name_short": "百度",
    "stock_code": "09888.HK",
    "stock_exchange": "HKEX",
    "data_source": "HKEX 披露易",
    "collected_at": "2026-03-14T19:28:26.892811",
    "quality_level": "L1",
    "confidence_score": "1.0",
    "quality_score": 1.0,
    "cleaned_at": "2026-03-14T19:28:29.460533",
    "cleaned_version": "1.0"
  },
  {
    "company_id": "H09633",
    "name_cn_full": "农夫山泉股份有限公司",
    "name_en_full": "Nongfu Spring Co. , Ltd. ",
    "name_short": "农夫",
    "stock_code": "09633.HK",
    "stock_exchange": "HKEX",
    "data_source": "HKEX 披露易",
    "collected_at": "2026-03-14T19:28:26.892813",
    "quality_level": "L1",
    "confidence_score": "1.0",
    "quality_score": 1.0,
    "cleaned_at": "2026-03-14T19:28:29.460534",
    "cleaned_version": "1.0"
  },
  {
    "company_id": "H00941",
    "name_cn_full": "中国移动有限公司",
    "name_en_full": "China Mobile Limited",
    "name_short": "中国",
    "stock_code": "00941.HK",
    "stock_exchange": "HKEX",
    "data_source": "HKEX 披露易",
    "collected_at": "2026-03-14T19:28:26.892814",
    "quality_level": "L1",
    "confidence_score": "1.0",
    "quality_score": 1.0,
    "cleaned_at": "2026-03-14T19:28:29.460535",
    "cleaned_version": "1.0"
  },
  {
    "company_id": "H00762",
    "name_cn_full": "中国联合网络通信有限公司",
    "name_en_full": "China Unicom (Hong Kong) Limited",
    "name_short": "中国",
    "stock_code": "00762.HK",
    "stock_exchange": "HKEX",
    "data_source": "HKEX 披露易",
    "collected_at": "2026-03-14T19:28:26.892815",
    "quality_level": "L1",
    "confidence_score": "1.0",
    "quality_score": 1.0,
    "cleaned_at": "2026-03-14T19:28:29.460535",
    "cleaned_version": "1.0"
  },
  {
    "company_id": "H00386",
    "name_cn_full": "中国石油化工股份有限公司",
    "name_en_full": "Sinopec Corp. ",
    "name_short": "中国",
    "stock_code": "00386.HK",
    "stock_exchange": "HKEX",
    "data_source": "HKEX 披露易",
    "collected_at": "2026-03-14T19:28:26.892816",
    "quality_level": "L1",
    "confidence_score": "1.0",
    "quality_score": 1.0,
    "cleaned_at": "2026-03-14T19:28:29.460536",
    "cleaned_version": "1.0"
  },
  {
    "company_id": "H00857",
    "name_cn_full": "中国石油天然气股份有限公司",
    "name_en_full": "Petrochina Company Limited",
    "name_short": "中国",
    "stock_code": "00857.HK",
    "stock_exchange": "HKEX",
    "data_source": "HKEX 披露易",
    "collected_at": "2026-03-14T19:28:26.892817",
    "quality_level": "L1",
    "confidence_score": "1.0",
    "quality_score": 1.0,
    "cleaned_at": "2026-03-14T19:28:29.460537",
    "cleaned_version": "1.0"
  },
  {
    "company_id": "H03988",
    "name_cn_full": "中国银行股份有限公司",
    "name_en_full": "Bank Of China Limited",
    "name_short": "中国",
    "stock_code": "03988.HK",
    "stock_exchange": "HKEX",
    "data_source": "HKEX 披露易",
    "collected_at": "2026-03-14T19:28:26.892818",
    "quality_level": "L1",
    "confidence_score": "1.0",
    "quality_score": 1.0,
    "cleaned_at": "2026-03-14T19:28:29.460538",
    "cleaned_version": "1.0"
  },
  {
    "company_id": "H01398",
    "name_cn_full": "中国工商银行股份有限公司",
    "name_en_full": "Industrial And Commercial Bank Of China Limited",
    "name_short": "中国",
    "stock_code": "01398.HK",
    "stock_exchange": "HKEX",
    "data_source": "HKEX 披露易",
    "collected_at": "2026-03-14T19:28:26.892819",
    "quality_level": "L1",
    "confidence_score": "1.0",
    "quality_score": 1.0,
    "cleaned_at": "2026-03-14T19:28:29.460538",
    "cleaned_version": "1.0"
  },
  {
    "company_id": "H00939",
    "name_cn_full": "中国建设银行股份有限公司",
    "name_en_full": "China Construction Bank Corporation",
    "name_short": "中国",
    "stock_code": "00939.HK",
    "stock_exchange": "HKEX",
    "data_source": "HKEX 披露易",
    "collected_at": "2026-03-14T19:28:26.892820",
    "quality_level": "L1",
    "confidence_score": "1.0",
    "quality_score": 1.0,
    "cleaned_at": "2026-03-14T19:28:29.460539",
    "cleaned_version": "1.0"
  },
  {
    "company_id": "H02318",
    "name_cn_full": "中国平安保险股份有限公司",
    "name_en_full": "Ping An Insurance (Group) Company Of China, Ltd. ",
    "name_short": "中国",
    "stock_code": "02318.HK",
    "stock_exchange": "HKEX",
    "data_source": "HKEX 披露易",
    "collected_at": "2026-03-14T19:28:26.892821",
    "quality_level": "L1",
    "confidence_score": "1.0",
    "quality_score": 1.0,
    "cleaned_at": "2026-03-14T19:28:29.460540",
    "cleaned_version": "1.0"
  },
  {
    "company_id": "H02628",
    "name_cn_full": "中国人寿保险股份有限公司",
    "name_en_full": "China Life Insurance Company Limited",
    "name_short": "中国",
    "stock_code": "02628.HK",
    "stock_exchange": "HKEX",
    "data_source": "HKEX 披露易",
    "collected_at": "2026-03-14T19:28:26.892822",
    "quality_level": "L1",
    "confidence_score": "1.0",
    "quality_score": 1.0,
    "cleaned_at": "2026-03-14T19:28:29.460540",
    "cleaned_version": "1.0"
  },
  {
    "company_id": "H01024",
    "name_cn_full": "快手科技股份有限公司",
    "name_en_full": "Kuaishou Technology",
    "name_short": "快手",
    "stock_code": "01024.HK",
    "stock_exchange": "HKEX",
    "data_source": "HKEX 披露易",
    "collected_at": "2026-03-14T19:28:26.892823",
    "quality_level": "L1",
    "confidence_score": "1.0",
    "quality_score": 1.0,
    "cleaned_at": "2026-03-14T19:28:29.460541",
    "cleaned_version": "1.0"
  },
  {
    "company_id": "H09626",
    "name_cn_full": "哔哩哔哩股份有限公司",
    "name_en_full": "Bilibili Inc. ",
    "name_short": "哔哩",
    "stock_code": "09626.HK",
    "stock_exchange": "HKEX",
    "data_source": "HKEX 披露易",
    "collected_at": "2026-03-14T19:28:26.892825",
    "quality_level": "L1",
    "confidence_score": "1.0",
    "quality_score": 1.0,
    "cleaned_at": "2026-03-14T19:28:29.460542",
    "cleaned_version": "1.0"
  },
  {
    "company_id": "H09866",
    "name_cn_full": "蔚来股份有限公司",
    "name_en_full": "Nio Inc. ",
    "name_short": "蔚来",
    "stock_code": "09866.HK",
    "stock_exchange": "HKEX",
    "data_source": "HKEX 披露易",
    "collected_at": "2026-03-14T19:28:26.892826",
    "quality_level": "L1",
    "confidence_score": "1.0",
    "quality_score": 1.0,
    "cleaned_at": "2026-03-14T19:28:29.460543",
    "cleaned_version": "1.0"
  },
  {
    "company_id": "H09868",
    "name_cn_full": "小鹏汽车股份有限公司",
    "name_en_full": "Xpeng Inc. ",
    "name_short": "小鹏",
    "stock_code": "09868.HK",
    "stock_exchange": "HKEX",
    "data_source": "HKEX 披露易",
    "collected_at": "2026-03-14T19:28:26.892827",
    "quality_level": "L1",
    "confidence_score": "1.0",
    "quality_score": 1.0,
    "cleaned_at": "2026-03-14T19:28:29.460543",
    "cleaned_version": "1.0"
  },
  {
    "company_id": "H02015",
    "name_cn_full": "理想汽车股份有限公司",
    "name_en_full": "Li Auto Inc. ",
    "name_short": "理想",
    "stock_code": "02015.HK",
    "stock_exchange": "HKEX",
    "data_source": "HKEX 披露易",
    "collected_at": "2026-03-14T19:28:26.892828",
    "quality_level": "L1",
    "confidence_score": "1.0",
    "quality_score": 1.0,
    "cleaned_at": "2026-03-14T19:28:29.460544",
    "cleaned_version": "1.0"
  },
  {
    "company_id": "H00291",
    "name_cn_full": "华润啤酒控股有限公司",
    "name_en_full": "China Resources Beer Holdings Company Limited",
    "name_short": "华润",
    "stock_code": "00291.HK",
    "stock_exchange": "HKEX",
    "data_source": "HKEX 披露易",
    "collected_at": "2026-03-14T19:28:26.892831",
    "quality_level": "L1",
    "confidence_score": "1.0",
    "quality_score": 1.0,
    "cleaned_at": "2026-03-14T19:28:29.460545",
    "cleaned_version": "1.0"
  },
  {
    "company_id": "H00101",
    "name_cn_full": "恒隆集团有限公司",
    "name_en_full": "Hang Lung Group Limited",
    "name_short": "恒隆",
    "stock_code": "00101.HK",
    "stock_exchange": "HKEX",
    "data_source": "HKEX 披露易",
    "collected_at": "2026-03-14T19:28:26.892832",
    "quality_level": "L1",
    "confidence_score": "1.0",
    "quality_score": 1.0,
    "cleaned_at": "2026-03-14T19:28:29.460545",
    "cleaned_version": "1.0"
  },
  {
    "company_id": "H00688",
    "name_cn_full": "中国海外发展有限公司",
    "name_en_full": "China Overseas Land & Investment Limited",
    "name_short": "中国",
    "stock_code": "00688.HK",
    "stock_exchange": "HKEX",
    "data_source": "HKEX 披露易",
    "collected_at": "2026-03-14T19:28:26.892833",
    "quality_level": "L1",
    "confidence_score": "1.0",
    "quality_score": 1.0,
    "cleaned_at": "2026-03-14T19:28:29.460546",
    "cleaned_version": "1.0"
  },
  {
    "company_id": "H01109",
    "name_cn_full": "华润置地有限公司",
    "name_en_full": "China Resources Land Limited",
    "name_short": "华润",
    "stock_code": "01109.HK",
    "stock_exchange": "HKEX",
    "data_source": "HKEX 披露易",
    "collected_at": "2026-03-14T19:28:26.892834",
    "quality_level": "L1",
    "confidence_score": "1.0",
    "quality_score": 1.0,
    "cleaned_at": "2026-03-14T19:28:29.460547",
    "cleaned_version": "1.0"
  },
  {
    "company_id": "H02007",
    "name_cn_full": "碧桂园控股有限公司",
    "name_en_full": "Country Garden Holdings Company Limited",
    "name_short": "碧桂",
    "stock_code": "02007.HK",
    "stock_exchange": "HKEX",
    "data_source": "HKEX 披露易",
    "collected_at": "2026-03-14T19:28:26.892835",
    "quality_level": "L1",
    "confidence_score": "1.0",
    "quality_score": 1.0,
    "cleaned_at": "2026-03-14T19:28:29.460548",
    "cleaned_version": "1.0"
  },
  {
    "company_id": "H00175",
    "name_cn_full": "吉利汽车控股有限公司",
    "name_en_full": "Geely Automobile Holdings Limited",
    "name_short": "吉利",
    "stock_code": "00175.HK",
    "stock_exchange": "HKEX",
    "data_source": "HKEX 披露易",
    "collected_at": "2026-03-14T19:28:26.892836",
    "quality_level": "L1",
    "confidence_score": "1.0",
    "quality_score": 1.0,
    "cleaned_at": "2026-03-14T19:28:29.460548",
    "cleaned_version": "1.0"
  },
  {
    "company_id": "H02333",
    "name_cn_full": "长城汽车股份有限公司",
    "name_en_full": "Great Wall Motor Company Limited",
    "name_short": "长城",
    "stock_code": "02333.HK",
    "stock_exchange": "HKEX",
    "data_source": "HKEX 披露易",
    "collected_at": "2026-03-14T19:28:26.892837",
    "quality_level": "L1",
    "confidence_score": "1.0",
    "quality_score": 1.0,
    "cleaned_at": "2026-03-14T19:28:29.460549",
    "cleaned_version": "1.0"
  },
  {
    "company_id": "H00489",
    "name_cn_full": "东风汽车集团股份有限公司",
    "name_en_full": "Dongfeng Motor Group Company Limited",
    "name_short": "东风",
    "stock_code": "00489.HK",
    "stock_exchange": "HKEX",
    "data_source": "HKEX 披露易",
    "collected_at": "2026-03-14T19:28:26.892839",
    "quality_level": "L1",
    "confidence_score": "1.0",
    "quality_score": 1.0,
    "cleaned_at": "2026-03-14T19:28:29.460550",
    "cleaned_version": "1.0"
  },
  {
    "company_id": "H02382",
    "name_cn_full": "舜宇光学科技集团股份有限公司",
    "name_en_full": "Sunny Optical Technology (Group) Company Limited",
    "name_short": "舜宇",
    "stock_code": "02382.HK",
    "stock_exchange": "HKEX",
    "data_source": "HKEX 披露易",
    "collected_at": "2026-03-14T19:28:26.892840",
    "quality_level": "L1",
    "confidence_score": "1.0",
    "quality_score": 1.0,
    "cleaned_at": "2026-03-14T19:28:29.460550",
    "cleaned_version": "1.0"
  },
  {
    "company_id": "H00763",
    "name_cn_full": "中兴通讯股份有限公司",
    "name_en_full": "Zte Corporation",
    "name_short": "中兴",
    "stock_code": "00763.HK",
    "stock_exchange": "HKEX",
    "data_source": "HKEX 披露易",
    "collected_at": "2026-03-14T19:28:26.892841",
    "quality_level": "L1",
    "confidence_score": "1.0",
    "quality_score": 1.0,
    "cleaned_at": "2026-03-14T19:28:29.460551",
    "cleaned_version": "1.0"
  },
  {
    "company_id": "H00005",
    "name_cn_full": "汇丰控股有限公司",
    "name_en_full": "Hsbc Holdings Plc",
    "name_short": "汇丰",
    "stock_code": "00005.HK",
    "stock_exchange": "HKEX",
    "data_source": "HKEX 披露易",
    "collected_at": "2026-03-14T19:28:26.892842",
    "quality_level": "L1",
    "confidence_score": "1.0",
    "quality_score": 1.0,
    "cleaned_at": "2026-03-14T19:28:29.460552",
    "cleaned_version": "1.0"
  },
  {
    "company_id": "H00003",
    "name_cn_full": "香港中华煤气有限公司",
    "name_en_full": "The Hong Kong And China Gas Company Limited",
    "name_short": "香港",
    "stock_code": "00003.HK",
    "stock_exchange": "HKEX",
    "data_source": "HKEX 披露易",
    "collected_at": "2026-03-14T19:28:26.892843",
    "quality_level": "L1",
    "confidence_score": "1.0",
    "quality_score": 1.0,
    "cleaned_at": "2026-03-14T19:28:29.460553",
    "cleaned_version": "1.0"
  },
  {
    "company_id": "H00016",
    "name_cn_full": "新鸿基地产发展有限公司",
    "name_en_full": "Sun Hung Kai Properties Limited",
    "name_short": "新鸿",
    "stock_code": "00016.HK",
    "stock_exchange": "HKEX",
    "data_source": "HKEX 披露易",
    "collected_at": "2026-03-14T19:28:26.892844",
    "quality_level": "L1",
    "confidence_score": "1.0",
    "quality_score": 1.0,
    "cleaned_at": "2026-03-14T19:28:29.460553",
    "cleaned_version": "1.0"
  },
  {
    "company_id": "H00011",
    "name_cn_full": "恒生银行有限公司",
    "name_en_full": "Hang Seng Bank Limited",
    "name_short": "恒生",
    "stock_code": "00011.HK",
    "stock_exchange": "HKEX",
    "data_source": "HKEX 披露易",
    "collected_at": "2026-03-14T19:28:26.892845",
    "quality_level": "L1",
    "confidence_score": "1.0",
    "quality_score": 1.0,
    "cleaned_at": "2026-03-14T19:28:29.460554",
    "cleaned_version": "1.0"
  },
  {
    "company_id": "H00012",
    "name_cn_full": "恒基兆业地产有限公司",
    "name_en_full": "Henderson Land Development Company Limited",
    "name_short": "恒基",
    "stock_code": "00012.HK",
    "stock_exchange": "HKEX",
    "data_source": "HKEX 披露易",
    "collected_at": "2026-03-14T19:28:26.892846",
    "quality_level": "L1",
    "confidence_score": "1.0",
    "quality_score": 1.0,
    "cleaned_at": "2026-03-14T19:28:29.460555",
    "cleaned_version": "1.0"
  },
  {
    "company_id": "H00002",
    "name_cn_full": "中电控股有限公司",
    "name_en_full": "Clp Holdings Limited",
    "name_short": "中电",
    "stock_code": "00002.HK",
    "stock_exchange": "HKEX",
    "data_source": "HKEX 披露易",
    "collected_at": "2026-03-14T19:28:26.892847",
    "quality_level": "L1",
    "confidence_score": "1.0",
    "quality_score": 1.0,
    "cleaned_at": "2026-03-14T19:28:29.460556",
    "cleaned_version": "1.0"
  },
  {
    "company_id": "H00006",
    "name_cn_full": "电能实业有限公司",
    "name_en_full": "Power Assets Holdings Limited",
    "name_short": "电能",
    "stock_code": "00006.HK",
    "stock_exchange": "HKEX",
    "data_source": "HKEX 披露易",
    "collected_at": "2026-03-14T19:28:26.892848",
    "quality_level": "L1",
    "confidence_score": "1.0",
    "quality_score": 1.0,
    "cleaned_at": "2026-03-14T19:28:29.460556",
    "cleaned_version": "1.0"
  },
  {
    "company_id": "H00083",
    "name_cn_full": "香港小轮有限公司",
    "name_en_full": "Hong Kong Ferry (Holdings) Company Limited",
    "name_short": "香港",
    "stock_code": "00083.HK",
    "stock_exchange": "HKEX",
    "data_source": "HKEX 披露易",
    "collected_at": "2026-03-14T19:28:26.892849",
    "quality_level": "L1",
    "confidence_score": "1.0",
    "quality_score": 1.0,
    "cleaned_at": "2026-03-14T19:28:29.460557",
    "cleaned_version": "1.0"
  },
  {
    "company_id": "H00019",
    "name_cn_full": "太古股份有限公司",
    "name_en_full": "Swire Pacific Limited",
    "name_short": "太古",
    "stock_code": "00019.HK",
    "stock_exchange": "HKEX",
    "data_source": "HKEX 披露易",
    "collected_at": "2026-03-14T19:28:26.892850",
    "quality_level": "L1",
    "confidence_score": "1.0",
    "quality_score": 1.0,
    "cleaned_at": "2026-03-14T19:28:29.460558",
    "cleaned_version": "1.0"
  },
  {
    "company_id": "H00267",
    "name_cn_full": "中信股份有限公司",
    "name_en_full": "Citic Limited",
    "name_short": "中信",
    "stock_code": "00267.HK",
    "stock_exchange": "HKEX",
    "data_source": "HKEX 披露易",
    "collected_at": "2026-03-14T19:28:26.892852",
    "quality_level": "L1",
    "confidence_score": "1.0",
    "quality_score": 1.0,
    "cleaned_at": "2026-03-14T19:28:29.460559",
    "cleaned_version": "1.0"
  },
  {
    "company_id": "H00656",
    "name_cn_full": "复星国际有限公司",
    "name_en_full": "Fosun International Limited",
    "name_short": "复星",
    "stock_code": "00656.HK",
    "stock_exchange": "HKEX",
    "data_source": "HKEX 披露易",
    "collected_at": "2026-03-14T19:28:26.892853",
    "quality_level": "L1",
    "confidence_score": "1.0",
    "quality_score": 1.0,
    "cleaned_at": "2026-03-14T19:28:29.460559",
    "cleaned_version": "1.0"
  },
  {
    "company_id": "H01177",
    "name_cn_full": "中国生物制药有限公司",
    "name_en_full": "Sino Biopharmaceutical Limited",
    "name_short": "中国",
    "stock_code": "01177.HK",
    "stock_exchange": "HKEX",
    "data_source": "HKEX 披露易",
    "collected_at": "2026-03-14T19:28:26.892854",
    "quality_level": "L1",
    "confidence_score": "1.0",
    "quality_score": 1.0,
    "cleaned_at": "2026-03-14T19:28:29.460560",
    "cleaned_version": "1.0"
  },
  {
    "company_id": "H01093",
    "name_cn_full": "石药集团有限公司",
    "name_en_full": "Cspc Pharmaceutical Group Limited",
    "name_short": "石药",
    "stock_code": "01093.HK",
    "stock_exchange": "HKEX",
    "data_source": "HKEX 披露易",
    "collected_at": "2026-03-14T19:28:26.892855",
    "quality_level": "L1",
    "confidence_score": "1.0",
    "quality_score": 1.0,
    "cleaned_at": "2026-03-14T19:28:29.460561",
    "cleaned_version": "1.0"
  },
  {
    "company_id": "H02269",
    "name_cn_full": "药明生物技术有限公司",
    "name_en_full": "Wuxi Biologics (Cayman) Inc. ",
    "name_short": "药明",
    "stock_code": "02269.HK",
    "stock_exchange": "HKEX",
    "data_source": "HKEX 披露易",
    "collected_at": "2026-03-14T19:28:26.892856",
    "quality_level": "L1",
    "confidence_score": "1.0",
    "quality_score": 1.0,
    "cleaned_at": "2026-03-14T19:28:29.460561",
    "cleaned_version": "1.0"
  },
  {
    "company_id": "H02618",
    "name_cn_full": "京东物流股份有限公司",
    "name_en_full": "Jd Logistics, Inc. ",
    "name_short": "京东",
    "stock_code": "02618.HK",
    "stock_exchange": "HKEX",
    "data_source": "HKEX 披露易",
    "collected_at": "2026-03-14T19:28:26.892857",
    "quality_level": "L1",
    "confidence_score": "1.0",
    "quality_score": 1.0,
    "cleaned_at": "2026-03-14T19:28:29.460562",
    "cleaned_version": "1.0"
  },
  {
    "company_id": "H09923",
    "name_cn_full": "贝壳找房科技有限公司",
    "name_en_full": "Ke Holdings Inc. ",
    "name_short": "贝壳",
    "stock_code": "09923.HK",
    "stock_exchange": "HKEX",
    "data_source": "HKEX 披露易",
    "collected_at": "2026-03-14T19:28:26.892858",
    "quality_level": "L1",
    "confidence_score": "1.0",
    "quality_score": 1.0,
    "cleaned_at": "2026-03-14T19:28:29.460563",
    "cleaned_version": "1.0"
  },
  {
    "company_id": "H09999",
    "name_cn_full": "网易股份有限公司",
    "name_en_full": "Netease, Inc. ",
    "name_short": "网易",
    "stock_code": "09999.HK",
    "stock_exchange": "HKEX",
    "data_source": "HKEX 披露易",
    "collected_at": "2026-03-14T19:28:26.892859",
    "quality_level": "L1",
    "confidence_score": "1.0",
    "quality_score": 1.0,
    "cleaned_at": "2026-03-14T19:28:29.460564",
    "cleaned_version": "1.0"
  },
  {
    "company_id": "H00772",
    "name_cn_full": "阅文集团有限公司",
    "name_en_full": "China Literature Limited",
    "name_short": "阅文",
    "stock_code": "00772.HK",
    "stock_exchange": "HKEX",
    "data_source": "HKEX 披露易",
    "collected_at": "2026-03-14T19:28:26.892860",
    "quality_level": "L1",
    "confidence_score": "1.0",
    "quality_score": 1.0,
    "cleaned_at": "2026-03-14T19:28:29.460564",
    "cleaned_version": "1.0"
  },
  {
    "company_id": "UBABA",
    "name_cn_full": "阿里巴巴集团控股有限公司",
    "name_en_full": "Alibaba Group Holding Limited",
    "name_short": "阿里",
    "stock_code": "BABA",
    "stock_exchange": "NASDAQ",
    "data_source": "SEC EDGAR",
    "collected_at": "2026-03-14T19:28:26.892899",
    "quality_level": "L1",
    "confidence_score": "1.0",
    "quality_score": 1.0,
    "cleaned_at": "2026-03-14T19:28:29.460565",
    "cleaned_version": "1.0"
  },
  {
    "company_id": "UPDD",
    "name_cn_full": "拼多多控股有限公司",
    "name_en_full": "Pdd Holdings Inc. ",
    "name_short": "拼多",
    "stock_code": "PDD",
    "stock_exchange": "NASDAQ",
    "data_source": "SEC EDGAR",
    "collected_at": "2026-03-14T19:28:26.892903",
    "quality_level": "L1",
    "confidence_score": "1.0",
    "quality_score": 1.0,
    "cleaned_at": "2026-03-14T19:28:29.460566",
    "cleaned_version": "1.0"
  },
  {
    "company_id": "UIQ",
    "name_cn_full": "爱奇艺股份有限公司",
    "name_en_full": "Iqiyi, Inc. ",
    "name_short": "爱奇",
    "stock_code": "IQ",
    "stock_exchange": "NASDAQ",
    "data_source": "SEC EDGAR",
    "collected_at": "2026-03-14T19:28:26.892912",
    "quality_level": "L1",
    "confidence_score": "1.0",
    "quality_score": 1.0,
    "cleaned_at": "2026-03-14T19:28:29.460566",
    "cleaned_version": "1.0"
  },
  {
    "company_id": "UVIPS",
    "name_cn_full": "唯品会控股有限公司",
    "name_en_full": "Vipshop Holdings Limited",
    "name_short": "唯品",
    "stock_code": "VIPS",
    "stock_exchange": "NASDAQ",
    "data_source": "SEC EDGAR",
    "collected_at": "2026-03-14T19:28:26.892913",
    "quality_level": "L1",
    "confidence_score": "1.0",
    "quality_score": 1.0,
    "cleaned_at": "2026-03-14T19:28:29.460567",
    "cleaned_version": "1.0"
  },
  {
    "company_id": "UWB",
    "name_cn_full": "微博股份有限公司",
    "name_en_full": "Weibo Corporation",
    "name_short": "微博",
    "stock_code": "WB",
    "stock_exchange": "NASDAQ",
    "data_source": "SEC EDGAR",
    "collected_at": "2026-03-14T19:28:26.892914",
    "quality_level": "L1",
    "confidence_score": "1.0",
    "quality_score": 1.0,
    "cleaned_at": "2026-03-14T19:28:29.460568",
    "cleaned_version": "1.0"
  },
  {
    "company_id": "UDIDI",
    "name_cn_full": "滴滴出行科技有限公司",
    "name_en_full": "Didi Global Inc. ",
    "name_short": "滴滴",
    "stock_code": "DIDI",
    "stock_exchange": "NYSE",
    "data_source": "SEC EDGAR",
    "collected_at": "2026-03-14T19:28:26.892915",
    "quality_level": "L1",
    "confidence_score": "1.0",
    "quality_score": 1.0,
    "cleaned_at": "2026-03-14T19:28:29.460568",
    "cleaned_version": "1.0"
  },
  {
    "company_id": "UTME",
    "name_cn_full": "腾讯音乐娱乐集团",
    "name_en_full": "Tencent Music Entertainment Group",
    "name_short": "腾讯",
    "stock_code": "TME",
    "stock_exchange": "NYSE",
    "data_source": "SEC EDGAR",
    "collected_at": "2026-03-14T19:28:26.892916",
    "quality_level": "L1",
    "confidence_score": "1.0",
    "quality_score": 1.0,
    "cleaned_at": "2026-03-14T19:28:29.460569",
    "cleaned_version": "1.0"
  },
  {
    "company_id": "UYMM",
    "name_cn_full": "满帮集团股份有限公司",
    "name_en_full": "Full Truck Alliance Co. Ltd. ",
    "name_short": "满帮",
    "stock_code": "YMM",
    "stock_exchange": "NYSE",
    "data_source": "SEC EDGAR",
    "collected_at": "2026-03-14T19:28:26.892917",
    "quality_level": "L1",
    "confidence_score": "1.0",
    "quality_score": 1.0,
    "cleaned_at": "2026-03-14T19:28:29.460570",
    "cleaned_version": "1.0"
  },
  {
    "company_id": "UDOYU",
    "name_cn_full": "斗鱼网络科技有限公司",
    "name_en_full": "Douyu International Holdings Limited",
    "name_short": "斗鱼",
    "stock_code": "DOYU",
    "stock_exchange": "NYSE",
    "data_source": "SEC EDGAR",
    "collected_at": "2026-03-14T19:28:26.892920",
    "quality_level": "L1",
    "confidence_score": "1.0",
    "quality_score": 1.0,
    "cleaned_at": "2026-03-14T19:28:29.460571",
    "cleaned_version": "1.0"
  },
  {
    "company_id": "UFUTU",
    "name_cn_full": "富途控股有限公司",
    "name_en_full": "Futu Holdings Limited",
    "name_short": "富途",
    "stock_code": "FUTU",
    "stock_exchange": "NYSE",
    "data_source": "SEC EDGAR",
    "collected_at": "2026-03-14T19:28:26.892921",
    "quality_level": "L1",
    "confidence_score": "1.0",
    "quality_score": 1.0,
    "cleaned_at": "2026-03-14T19:28:29.460571",
    "cleaned_version": "1.0"
  },
  {
    "company_id": "UUP",
    "name_cn_full": "Upside 控股有限公司",
    "name_en_full": "Upside Holdings Limited",
    "name_short": "Up",
    "stock_code": "UP",
    "stock_exchange": "NYSE",
    "data_source": "SEC EDGAR",
    "collected_at": "2026-03-14T19:28:26.892922",
    "quality_level": "L1",
    "confidence_score": "1.0",
    "quality_score": 1.0,
    "cleaned_at": "2026-03-14T19:28:29.460572",
    "cleaned_version": "1.0"
  },
  {
    "company_id": "UTIGR",
    "name_cn_full": "老虎证券股份有限公司",
    "name_en_full": "Up Fintech Holding Limited",
    "name_short": "老虎",
    "stock_code": "TIGR",
    "stock_exchange": "NYSE",
    "data_source": "SEC EDGAR",
    "collected_at": "2026-03-14T19:28:26.892923",
    "quality_level": "L1",
    "confidence_score": "1.0",
    "quality_score": 1.0,
    "cleaned_at": "2026-03-14T19:28:29.460573",
    "cleaned_version": "1.0"
  },
  {
    "company_id": "UMOMO",
    "name_cn_full": "陌陌科技有限公司",
    "name_en_full": "Hello Group Inc. ",
    "name_short": "陌陌",
    "stock_code": "MOMO",
    "stock_exchange": "NYSE",
    "data_source": "SEC EDGAR",
    "collected_at": "2026-03-14T19:28:26.892928",
    "quality_level": "L1",
    "confidence_score": "1.0",
    "quality_score": 1.0,
    "cleaned_at": "2026-03-14T19:28:29.460573",
    "cleaned_version": "1.0"
  },
  {
    "company_id": "UCAAS",
    "name_cn_full": "中国汽车系统",
    "name_en_full": "China Automotive Systems, Inc. ",
    "name_short": "中国",
    "stock_code": "CAAS",
    "stock_exchange": "NYSE",
    "data_source": "SEC EDGAR",
    "collected_at": "2026-03-14T19:28:26.892930",
    "quality_level": "L1",
    "confidence_score": "1.0",
    "quality_score": 1.0,
    "cleaned_at": "2026-03-14T19:28:29.460574",
    "cleaned_version": "1.0"
  },
  {
    "company_id": "UTOUR",
    "name_cn_full": "途牛旅游网",
    "name_en_full": "Tuniu Corporation",
    "name_short": "途牛",
    "stock_code": "TOUR",
    "stock_exchange": "NYSE",
    "data_source": "SEC EDGAR",
    "collected_at": "2026-03-14T19:28:26.892936",
    "quality_level": "L1",
    "confidence_score": "1.0",
    "quality_score": 1.0,
    "cleaned_at": "2026-03-14T19:28:29.460575",
    "cleaned_version": "1.0"
  },
  {
    "company_id": "UFINV",
    "name_cn_full": "金融壹账通",
    "name_en_full": "Finvolution Group",
    "name_short": "金融",
    "stock_code": "FINV",
    "stock_exchange": "NYSE",
    "data_source": "SEC EDGAR",
    "collected_at": "2026-03-14T19:28:26.892938",
    "quality_level": "L1",
    "confidence_score": "1.0",
    "quality_score": 1.0,
    "cleaned_at": "2026-03-14T19:28:29.460576",
    "cleaned_version": "1.0"
  },
  {
    "company_id": "UCDEL",
    "name_cn_full": "credible 科技",
    "name_en_full": "Credit Acceptance Corporation",
    "name_short": " c",
    "stock_code": "CDEL",
    "stock_exchange": "NYSE",
    "data_source": "SEC EDGAR",
    "collected_at": "2026-03-14T19:28:26.892941",
    "quality_level": "L1",
    "confidence_score": "1.0",
    "quality_score": 1.0,
    "cleaned_at": "2026-03-14T19:28:29.460576",
    "cleaned_version": "1.0"
  },
  {
    "company_id": "UDQ",
    "name_cn_full": "大全新能源",
    "name_en_full": "Daqo New Energy Corp. ",
    "name_short": "大全",
    "stock_code": "DQ",
    "stock_exchange": "NYSE",
    "data_source": "SEC EDGAR",
    "collected_at": "2026-03-14T19:28:26.892945",
    "quality_level": "L1",
    "confidence_score": "1.0",
    "quality_score": 1.0,
    "cleaned_at": "2026-03-14T19:28:29.460577",
    "cleaned_version": "1.0"
  },
  {
    "company_id": "UCSIQ",
    "name_cn_full": "阿特斯太阳能",
    "name_en_full": "Canadian Solar Inc. ",
    "name_short": "阿特",
    "stock_code": "CSIQ",
    "stock_exchange": "NYSE",
    "data_source": "SEC EDGAR",
    "collected_at": "2026-03-14T19:28:26.892946",
    "quality_level": "L1",
    "confidence_score": "1.0",
    "quality_score": 1.0,
    "cleaned_at": "2026-03-14T19:28:29.460578",
    "cleaned_version": "1.0"
  },
  {
    "company_id": "UMAXN",
    "name_cn_full": "Maxeon Solar",
    "name_en_full": "Maxeon Solar Technologies, Ltd. ",
    "name_short": "Ma",
    "stock_code": "MAXN",
    "stock_exchange": "NYSE",
    "data_source": "SEC EDGAR",
    "collected_at": "2026-03-14T19:28:26.892950",
    "quality_level": "L1",
    "confidence_score": "1.0",
    "quality_score": 1.0,
    "cleaned_at": "2026-03-14T19:28:29.460578",
    "cleaned_version": "1.0"
  },
  {
    "company_id": "UMP",
    "name_cn_full": "MP Materials",
    "name_en_full": "Mp Materials Corp. ",
    "name_short": "MP",
    "stock_code": "MP",
    "stock_exchange": "NYSE",
    "data_source": "SEC EDGAR",
    "collected_at": "2026-03-14T19:28:26.892958",
    "quality_level": "L1",
    "confidence_score": "1.0",
    "quality_score": 1.0,
    "cleaned_at": "2026-03-14T19:28:29.460579",
    "cleaned_version": "1.0"
  },
  {
    "company_id": "UFCX",
    "name_cn_full": "自由港麦克莫兰",
    "name_en_full": "Freeport-Mcmoran Inc. ",
    "name_short": "自由",
    "stock_code": "FCX",
    "stock_exchange": "NYSE",
    "data_source": "SEC EDGAR",
    "collected_at": "2026-03-14T19:28:26.892962",
    "quality_level": "L1",
    "confidence_score": "1.0",
    "quality_score": 1.0,
    "cleaned_at": "2026-03-14T19:28:29.460580",
    "cleaned_version": "1.0"
  },
  {
    "company_id": "S002594",
    "name_cn_full": "比亚迪汽车",
    "name_en_full": "Byd Auto",
    "name_short": "比亚",
    "stock_code": "002594",
    "stock_exchange": "SZSE",
    "data_source": "公开资料/独角兽榜单",
    "collected_at": "2026-03-14T19:28:26.893058",
    "quality_level": "L3",
    "confidence_score": "0.85",
    "quality_score": 0.9100000000000003,
    "cleaned_at": "2026-03-14T19:28:29.460581",
    "cleaned_version": "1.0"
  }
]